MANIFEST.in
README.rst
setup.py
django_ratchet_scss.egg-info/PKG-INFO
django_ratchet_scss.egg-info/SOURCES.txt
django_ratchet_scss.egg-info/dependency_links.txt
django_ratchet_scss.egg-info/requires.txt
django_ratchet_scss.egg-info/top_level.txt
ratchet_scss/__init__.py
ratchet_scss/admin.py
ratchet_scss/models.py
ratchet_scss/tests.py
ratchet_scss/views.py
ratchet_scss/static/badges.scss
ratchet_scss/static/bars.scss
ratchet_scss/static/base.scss
ratchet_scss/static/buttons.scss
ratchet_scss/static/cards.scss
ratchet_scss/static/docs.scss
ratchet_scss/static/forms.scss
ratchet_scss/static/mixins.scss
ratchet_scss/static/modals.scss
ratchet_scss/static/normalize.scss
ratchet_scss/static/popovers.scss
ratchet_scss/static/push.scss
ratchet_scss/static/ratchet.scss
ratchet_scss/static/ratchicons.scss
ratchet_scss/static/segmented-controls.scss
ratchet_scss/static/sliders.scss
ratchet_scss/static/table-views.scss
ratchet_scss/static/theme-android.scss
ratchet_scss/static/theme-ios.scss
ratchet_scss/static/toggles.scss
ratchet_scss/static/type.scss
ratchet_scss/static/variables.scss
ratchet_scss/static/fonts/ratchicons.eot
ratchet_scss/static/fonts/ratchicons.svg
ratchet_scss/static/fonts/ratchicons.ttf
ratchet_scss/static/fonts/ratchicons.woff
ratchet_scss/static/js/ratchet.js
ratchet_scss/static/js/ratchet.min.js